TerminalWriter.py
TerminalWriter-1.0.1.dist-info/WHEEL
TerminalWriter-1.0.1.dist-info/METADATA
TerminalWriter-1.0.1.dist-info/RECORD
