Metadata-Version: 1.2
Name: TerminalWriter
Version: 1.0.1
Summary: This module has functions to generate simple tabular reports.
Home-page: https://github.com/N-C-C/TerminalWriter
License: UNKNOWN
Author: John Glasgow
Author-email: jglasgow@northampton.edu
Requires-Python: >=3
Classifier: License :: OSI Approved :: MIT License
